round_a_number/__init__.py
round_a_number/rounding_downwards.py
round_a_number/rounding_upwards.py
round_a_number-0.1.0.dist-info/LICENSE.txt
round_a_number-0.1.0.dist-info/METADATA
round_a_number-0.1.0.dist-info/WHEEL
round_a_number-0.1.0.dist-info/top_level.txt
round_a_number-0.1.0.dist-info/RECORD
