Metadata-Version: 2.1
Name: round_a_number
Version: 0.1.0
Summary: A library that rounds a given number to either upwards or downwards as mentioned
Author: Vivek
Author-email: x23324902@student.ncirl.ie
Requires-Python: >=3.6
License-File: LICENSE.txt
